pyobs/__init__.py
pyobs/base_classes.py
pyobs/core.py
pyobs/events.py
pyobs/exceptions.py
pyobs/requests.py
pyobs-0.1.dist-info/LICENSE
pyobs-0.1.dist-info/METADATA
pyobs-0.1.dist-info/WHEEL
pyobs-0.1.dist-info/top_level.txt
pyobs-0.1.dist-info/RECORD
