Metadata-Version: 2.1
Name: pyobs
Version: 0.1
Summary: Python library to communicate with an obs-websocket server.
Home-page: https://github.com/Adirio/pyobs
Author: Adrián "Adirio" Orive
Author-email: adrian.orive.oneca@gmail.com
License: MIT
Download-URL: https://github.com/Adirio/pyobs/archive/0.1.tar.gz
Keywords: obs,obs-studio,websocket
Platform: UNKNOWN
Classifier: License :: OSI Approved :: MIT License
Classifier: Environment :: Plugins
Classifier: Intended Audience :: Developers
Classifier: Topic :: Software Development :: Libraries
Classifier: Development Status :: 4 - Beta
Classifier: Programming Language :: Python :: 2
Classifier: Programming Language :: Python :: 2.7
Classifier: Programming Language :: Python :: 3
Classifier: Programming Language :: Python :: 3.5
